bm/pythagorean_triples/__init__.py
bm/pythagorean_triples/py.typed
bm/pythagorean_triples/pythag3.py
bm/pythagorean_triples/cli/__init__.py
bm/pythagorean_triples/cli/py.typed
bm/pythagorean_triples/cli/pythag3.py
bm_pythagorean_triples-0.6.1.dist-info/entry_points.txt
bm_pythagorean_triples-0.6.1.dist-info/licenses/LICENSE
bm_pythagorean_triples-0.6.1.dist-info/WHEEL
bm_pythagorean_triples-0.6.1.dist-info/METADATA
bm_pythagorean_triples-0.6.1.dist-info/RECORD
