Metadata-Version: 2.4
Name: bm.pythagorean-triples
Version: 0.6.1
Summary: Pythagorean triples
Keywords: math,mathematics,pythagorean,triples
Author-email: "Geoffrey R. Scheller" <geoffrey@scheller.com>
Requires-Python: >=3.12
Classifier: Development Status :: 3 - Alpha
Classifier: Framework :: Pytest
Classifier: Intended Audience :: Education
Classifier: License :: OSI Approved :: Apache Software License
Classifier: Operating System :: OS Independent
Classifier: Programming Language :: Python :: 3.13
Classifier: Typing :: Typed
License-File: LICENSE
Requires-Dist: bm.integer-math >= 0.6.0
Requires-Dist: pythonic-fp.circulararray >= 5.1.0
Requires-Dist: pythonic-fp.fptools >= 3.0.0
Project-URL: Changelog, https://github.com/grscheller/bm-pythagorean-triples/blob/main/CHANGELOG.md
Project-URL: Documentation, https://grscheller.github.io/bm-docs/pythagorean-triples/
Project-URL: Homepage, https://github.com/grscheller/bm-docs/blob/main/README.md
Project-URL: Source, https://github.com/grscheller/bm-pythagorean-triples
